{
    "name": "Checkr",
    "description": "<p>Automated background screenings and driving records. Run background checks automatically and securely with our RESTful API. Checkr's color-coded dashboard makes it easy to browse and evaluate background reports that include national and county criminal records, driving history, SSN verification, previous addresses and more. Our simple and robust API lets you integrate in minutes. We provide a clean documentation and powerful developer tools. Receive real-time results in your application via webhooks.&nbsp;<\/p>",
    "image": "http:\/\/kinlane-productions.s3.amazonaws.com\/screen-capture-api\/10362-daniel-yanisse.jpg",
    "tags": [
        "api provider",
        "background check",
        "criminal check",
        "have api",
        "target"
    ],
    "created": "2019-12-19",
    "modified": "2019-12-19",
    "url": "https:\/\/raw.githubusercontent.com\/api-evangelist\/checkr\/master\/apis.json",
    "specificationVersion": "0.14",
    "apis": [
        {
            "name": "Checkr",
            "description": null,
            "image": "http:\/\/kinlane-productions.s3.amazonaws.com\/screen-capture-api\/10362-daniel-yanisse.jpg",
            "humanURL": "https:\/\/checkr.io\/",
            "baseURL": "",
            "tags": [],
            "properties": [
                {
                    "type": "x-openapi",
                    "url": "https:\/\/raw.githubusercontent.com\/api-evangelist\/1forge\/master\/checkr-openapi.json"
                },
                {
                    "type": "x-postman-collecction",
                    "url": "https:\/\/raw.githubusercontent.com\/api-evangelist\/1forge\/master\/checkr-postman-collection.json"
                }
            ]
        }
    ],
    "include": [],
    "x-common": [
        {
            "type": "Base",
            "url": "https:\/\/api.checkr.io"
        },
        {
            "type": "Crunchbase",
            "url": "https:\/\/crunchbase.com\/organization\/checkr"
        },
        {
            "type": "Developers",
            "url": "https:\/\/checkr.io\/docs"
        },
        {
            "type": "Twitter",
            "url": "https:\/\/twitter.com\/checkr"
        },
        {
            "type": "Twitter",
            "url": "https:\/\/twitter.com\/checkr_io"
        },
        {
            "type": "Website",
            "url": "https:\/\/checkr.io\/"
        }
    ]
}